Metadata-Version: 2.1
Name: rdsutils
Version: 0.0.3
Summary: A set of lightweight utilities
Home-page: 
Author: 
Author-email: 
Classifier: Programming Language :: Python :: 3
Classifier: Operating System :: OS Independent
Requires-Python: >=3.6
